frasco_geoip.py
setup.py
frasco_geoip.egg-info/PKG-INFO
frasco_geoip.egg-info/SOURCES.txt
frasco_geoip.egg-info/dependency_links.txt
frasco_geoip.egg-info/not-zip-safe
frasco_geoip.egg-info/requires.txt
frasco_geoip.egg-info/top_level.txt