Metadata-Version: 1.0
Name: frasco-geoip
Version: 0.1
Summary: pygeoip integration for Frasco
Home-page: http://github.com/frascoweb/frasco-geoip
Author: Maxime Bouroumeau-Fuseau
Author-email: maxime.bouroumeau@gmail.com
License: MIT
Platform: any
